signale/__init__.py
signale_logging-0.5.4.dist-info/METADATA
signale_logging-0.5.4.dist-info/WHEEL
signale_logging-0.5.4.dist-info/top_level.txt
signale_logging-0.5.4.dist-info/RECORD
