Metadata-Version: 2.1
Name: signale-logging
Version: 0.5.4
Summary: Elegant Console Logger For Python Command Line Apps
Home-page: https://github.com/MarcelWaldvogel/signale.py
Author: Shardul Nalegave and Marcel Waldvogel
Author-email: nalegaveshardul40@gmail.com, marcel.waldvogel@trifence.ch
License: MIT
Platform: UNKNOWN
Classifier: Development Status :: 4 - Beta
Classifier: Intended Audience :: Information Technology
Classifier: Intended Audience :: Developers
Classifier: Programming Language :: Python
Classifier: Programming Language :: Python :: 3
Classifier: License :: OSI Approved :: MIT License
Classifier: Operating System :: OS Independent
Classifier: Natural Language :: English
Classifier: Environment :: Console
Classifier: Environment :: No Input/Output (Daemon)
Classifier: Topic :: System :: Logging
Requires-Python: >=3.2
Requires-Dist: setuptools
